LICENSE.txt
MANIFEST.in
README.md
setup.py
prestio/prestio.cfg
prestio/prestio.py
prestio.egg-info/PKG-INFO
prestio.egg-info/SOURCES.txt
prestio.egg-info/dependency_links.txt
prestio.egg-info/entry_points.txt
prestio.egg-info/requires.txt
prestio.egg-info/top_level.txt