Metadata-Version: 2.1
Name: prestio
Version: 0.0.4
Summary: Plone REST API IO tool
Home-page: https://github.com/wobsta/prestio
Author: André Wobst
Author-email: project.prestio@wobsta.de
License: UNKNOWN
Platform: UNKNOWN
Classifier: Programming Language :: Python :: 3
Classifier: License :: OSI Approved :: GNU General Public License v2 or later (GPLv2+)
Classifier: Operating System :: OS Independent
